{
    "info": {
        "_postman_id": "c8e410be-0b97-5ea9-9555-860f1a69ede4",
        "name": "Users API",
        "schema": "https://schema.getpostman.com/json/collection/v2.0.0/collection.json"
    },
    "item": [
        {
            "name": "Get all users",
            "request": {
                "method": "GET",
                "header": [
                    {
                        "key": "Authorization",
                        "value": "eyJhbGciOiJIUzI1NiIsInR5cCI6IkpXVCJ9.eyJfaWQiOiI2MzljMTNmMjMzNTAyMjc5ODIzYjQzYjYiLCJpYXQiOjE2NzE3NzQyMTEsImV4cCI6MTY3MjAzMzQxMX0.bpZY4D1wv2Fl2QTZ-BOs05qOyxT3IOv1h6O3CCS2-Wk"
                    }
                ],
                "body": {
                    "mode": "formdata",
                    "formdata": []
                },
                "url": "http://127.0.0.1:5001/users"
            },
            "response": []
        },
        {
            "name": "User Login",
            "request": {
                "method": "POST",
                "header": [
                    {
                        "key": "Authorization",
                        "value": "eyJhbGciOiJIUzI1NiIsInR5cCI6IkpXVCJ9.eyJfaWQiOiI2MzhkOTJkNjAwYzFiNzIzMjdiNTE2MWQiLCJpYXQiOjE2NzAyMjI1NTEsImV4cCI6MTY3MDQ4MTc1MX0.zhyNqHnVYphWHNsaa1xCGQpxZBHc8de1WytVW1uxheU",
                        "disabled": true
                    },
                    {
                        "key": "Content-Type",
                        "value": "application/json"
                    }
                ],
                "body": {
                    "mode": "raw",
                    "raw": "{\r\n    \"email\": \"dhileep@gmail.com\",\r\n    \"password\": \"123456\"\r\n}"
                },
                "url": "localhost:5001/login"
            },
            "response": []
        },
        {
            "name": "User Registration",
            "request": {
                "method": "POST",
                "header": [
                    {
                        "key": "Content-Type",
                        "value": "application/json"
                    }
                ],
                "body": {
                    "mode": "raw",
                    "raw": "{\r\n    \"username\": \"dhileep\",\r\n    \"email\": \"dhileep@gmail.com\",\r\n    \"password\": \"123456\"\r\n}"
                },
                "url": "localhost:5001/register"
            },
            "response": []
        },
        {
            "name": "User Profile",
            "request": {
                "method": "GET",
                "header": [
                    {
                        "key": "Authorization",
                        "value": "eyJhbGciOiJIUzI1NiIsInR5cCI6IkpXVCJ9.eyJfaWQiOiI2M2E1NTQzMDBjMGY3YmE4ODRlOTdlOTEiLCJpYXQiOjE2NzE3NzkzNzYsImV4cCI6MTY3MjAzODU3Nn0.3iiFFP0Jq_jrFO6xMps1Flm79cZhxfmRtcvY-W7ozBE"
                    }
                ],
                "body": {
                    "mode": "formdata",
                    "formdata": []
                },
                "url": "localhost:5001/profile"
            },
            "response": []
        },
        {
            "name": "Logout",
            "request": {
                "method": "POST",
                "header": [
                    {
                        "key": "Authorization",
                        "value": "eyJhbGciOiJIUzI1NiIsInR5cCI6IkpXVCJ9.eyJfaWQiOiI2MzljMTNmMjMzNTAyMjc5ODIzYjQzYjYiLCJpYXQiOjE2NzE3ODE5MjEsImV4cCI6MTY3MjA0MTEyMX0.LjCSx5tWX1dQ0PVzoskRERwApgp9dRzT-JpTPtT_A1A"
                    }
                ],
                "body": {
                    "mode": "formdata",
                    "formdata": []
                },
                "url": "http://127.0.0.1:5000/logout"
            },
            "response": []
        }
    ]
}